{
  "main": {
    "id": "1d5dda5503c62736",
    "type": "split",
    "children": [
      {
        "id": "624331696104bdd2",
        "type": "tabs",
        "children": [
          {
            "id": "753a87c9575c7fed",
            "type": "leaf",
            "state": {
              "type": "markdown",
              "state": {
                "file": "Part 1/B - Javascript/0 Javascript Standard.md",
                "mode": "source",
                "source": false
              },
              "icon": "lucide-file",
              "title": "0 Javascript Standard"
            }
          },
          {
            "id": "ba898535efaf25fd",
            "type": "leaf",
            "state": {
              "type": "markdown",
              "state": {
                "file": "Part 1/B - Javascript/1. Javascript.md",
                "mode": "source",
                "source": false
              },
              "icon": "lucide-file",
              "title": "1. Javascript"
            }
          },
          {
            "id": "89729e99b39689a4",
            "type": "leaf",
            "state": {
              "type": "markdown",
              "state": {
                "file": "ReTopics/Javascript Variable Type/Medium Article about let var const.md",
                "mode": "source",
                "source": false
              },
              "icon": "lucide-file",
              "title": "Medium Article about let var const"
            }
          },
          {
            "id": "f68d382abb2bc7a2",
            "type": "leaf",
            "state": {
              "type": "markdown",
              "state": {
                "file": "Part 1/B - Javascript/0 Javascript Standard.md",
                "mode": "source",
                "source": false
              },
              "icon": "lucide-file",
              "title": "0 Javascript Standard"
            }
          }
        ],
        "currentTab": 3
      }
    ],
    "direction": "vertical"
  },
  "left": {
    "id": "db457c12b9e926a3",
    "type": "split",
    "children": [
      {
        "id": "dbb3cc0bc814db89",
        "type": "tabs",
        "children": [
          {
            "id": "1d510298a204f432",
            "type": "leaf",
            "state": {
              "type": "file-explorer",
              "state": {
                "sortOrder": "alphabetical"
              },
              "icon": "lucide-folder-closed",
              "title": "Files"
            }
          },
          {
            "id": "3a8fb7908e088ac2",
            "type": "leaf",
            "state": {
              "type": "search",
              "state": {
                "query": "",
                "matchingCase": false,
                "explainSearch": false,
                "collapseAll": false,
                "extraContext": false,
                "sortOrder": "alphabetical"
              },
              "icon": "lucide-search",
              "title": "Search"
            }
          },
          {
            "id": "3396f196964f2f1e",
            "type": "leaf",
            "state": {
              "type": "bookmarks",
              "state": {},
              "icon": "lucide-bookmark",
              "title": "Bookmarks"
            }
          },
          {
            "id": "8d0ba44c4e490fed",
            "type": "leaf",
            "state": {
              "type": "markdown",
              "state": {
                "file": "Part 1/A - Introduction to React/3. JSX.md",
                "mode": "source",
                "source": false
              },
              "icon": "lucide-file",
              "title": "3. JSX"
            }
          }
        ]
      }
    ],
    "direction": "horizontal",
    "width": 335.20000000000005
  },
  "right": {
    "id": "cfb98913b93fd8d1",
    "type": "split",
    "children": [
      {
        "id": "8617c1eca04d88ad",
        "type": "tabs",
        "children": [
          {
            "id": "b08b2a3406165db5",
            "type": "leaf",
            "state": {
              "type": "backlink",
              "state": {
                "file": "ReTopics/Callback Functions.md",
                "collapseAll": false,
                "extraContext": false,
                "sortOrder": "alphabetical",
                "showSearch": false,
                "searchQuery": "",
                "backlinkCollapsed": false,
                "unlinkedCollapsed": true
              },
              "icon": "links-coming-in",
              "title": "Backlinks for Callback Functions"
            }
          },
          {
            "id": "63222b3e64c40d3f",
            "type": "leaf",
            "state": {
              "type": "outgoing-link",
              "state": {
                "file": "ReTopics/Callback Functions.md",
                "linksCollapsed": false,
                "unlinkedCollapsed": true
              },
              "icon": "links-going-out",
              "title": "Outgoing links from Callback Functions"
            }
          },
          {
            "id": "f6c87ec534a8b1f4",
            "type": "leaf",
            "state": {
              "type": "tag",
              "state": {
                "sortOrder": "frequency",
                "useHierarchy": true
              },
              "icon": "lucide-tags",
              "title": "Tags"
            }
          },
          {
            "id": "d3d2327b23574994",
            "type": "leaf",
            "state": {
              "type": "outline",
              "state": {
                "file": "ReTopics/Callback Functions.md"
              },
              "icon": "lucide-list",
              "title": "Outline of Callback Functions"
            }
          }
        ],
        "currentTab": 3
      }
    ],
    "direction": "horizontal",
    "width": 300,
    "collapsed": true
  },
  "left-ribbon": {
    "hiddenItems": {
      "switcher:Open quick switcher": false,
      "graph:Open graph view": false,
      "canvas:Create new canvas": false,
      "daily-notes:Open today's daily note": false,
      "templates:Insert template": false,
      "command-palette:Open command palette": false
    }
  },
  "active": "f68d382abb2bc7a2",
  "lastOpenFiles": [
    "Part 1/B - Javascript/1. Javascript.md",
    "Javascript Runtime Described.md",
    "Screenshot 2025-01-05 at 3.03.05 AM.png",
    "Screenshot 2025-01-05 at 2.36.19 AM.png",
    "ReTopics/Javascript Variable Type/Medium Article about let var const.md",
    "Part 1/B - Javascript/0 Javascript Standard.md",
    "ReTopics/Javascript Functions/Callback Functions.md",
    "ReTopics/Javascript Variable Type/const.md",
    "ReTopics/Javascript Variable Type/let.md",
    "ReTopics/Javascript Variable Type",
    "ReTopics/JavaScript Function.md",
    "ReTopics/Javascript Functions",
    "Part 1/A - Introduction to React/4. Multiple Components.md",
    "Part 1/B - Javascript",
    "Part 1/A - Introduction to React/5.  props-passing data to components.md",
    "Part 1/A - Introduction to React/3. JSX.md",
    "Part 1/A - Introduction to React/2. Component.md",
    "Part 1/A - Introduction to React/1. -create-react-app.md",
    "Part 0 Fundamentals of Web Apps/14. JavaScript fatigue.md",
    "Part 0 Fundamentals of Web Apps/13. Full-stack web development.md",
    "Part 0 Fundamentals of Web Apps/12. JavaScript-libraries.md",
    "Part 0 Fundamentals of Web Apps/11. Single page app.md",
    "Part 0 Fundamentals of Web Apps/10. AJAX.md",
    "Part 0 Fundamentals of Web Apps/9.  Forms and HTTP POST.md",
    "Part 0 Fundamentals of Web Apps/8. Loading a page containing JavaScript - review.md",
    "Part 0 Fundamentals of Web Apps/7. CSS.md",
    "Part 0 Fundamentals of Web Apps/6. Manipulating the document object from console.md",
    "Part 0 Fundamentals of Web Apps/5. Document Object Model or Dom.md",
    "Part 0 Fundamentals of Web Apps/4. Event handlers and Callback functions.md",
    "Part 0 Fundamentals of Web Apps/3. Running application logic in the browser.md",
    "Part 1/A - Introduction to React",
    "B",
    "React.Dev",
    "\"ReTopics",
    "Part 1/A - Introduction to React/introdemo/public/vite.svg",
    "Part 1/A - Introduction to React/introdemo/package-lock.json",
    "Part 1/A - Introduction to React/introdemo/node_modules/es-abstract/tmp.mjs",
    "Part 1/A - Introduction to React/introdemo/node_modules/es-abstract/package.json",
    "Part 1/A - Introduction to React/introdemo/src/assets/react.svg",
    "images/Pasted image 20241231220925.png",
    "images/20241230180750.png"
  ]
}